cyphertext/__init__.py
cyphertext/common.py
cyphertext/cyphertext.py
cyphertext/encoder.py
cypher_text_toolkit-0.0.1.dist-info/LICENSE
cypher_text_toolkit-0.0.1.dist-info/METADATA
cypher_text_toolkit-0.0.1.dist-info/WHEEL
cypher_text_toolkit-0.0.1.dist-info/entry_points.txt
cypher_text_toolkit-0.0.1.dist-info/top_level.txt
cypher_text_toolkit-0.0.1.dist-info/RECORD
